lines_counter/__init__.py
lines_counter-1.0.2.dist-info/METADATA
lines_counter-1.0.2.dist-info/WHEEL
lines_counter-1.0.2.dist-info/top_level.txt
lines_counter-1.0.2.dist-info/RECORD
