Metadata-Version: 2.1
Name: lines-counter
Version: 1.0.2
Summary: A logical & physical lines counter for Python files
Home-page: https://github.com/LineCounters/LinesCounter
Author: LineCounters - UADY
